MANIFEST.in
setup.py
probe/__init__.py
probe/rdirwatcher/__init__.py
probe/rdirwatcher/rdirwatcher.py
probe/rdirwatcher/cfg/rdirwatcher.cfg
probe_rdirwatcher.egg-info/PKG-INFO
probe_rdirwatcher.egg-info/SOURCES.txt
probe_rdirwatcher.egg-info/dependency_links.txt
probe_rdirwatcher.egg-info/entry_points.txt
probe_rdirwatcher.egg-info/namespace_packages.txt
probe_rdirwatcher.egg-info/not-zip-safe
probe_rdirwatcher.egg-info/pbr.json
probe_rdirwatcher.egg-info/requires.txt
probe_rdirwatcher.egg-info/top_level.txt
test/test_rmdirwatcher.py