Metadata-Version: 1.0
Name: probe-rdirwatcher
Version: 0.0.8
Summary: watch remote directory for changes
Home-page: UNKNOWN
Author: Petr Zikan
Author-email: zikan.p@gmail.com
License: GPLv3
Platform: UNKNOWN
